sensenova/__init__.py
sensenova/_sensenova_scripts.py
sensenova/api_requestor.py
sensenova/cli.py
sensenova/error.py
sensenova/object_classes.py
sensenova/sensenova_object.py
sensenova/sensenova_response.py
sensenova/upload_progress.py
sensenova/util.py
sensenova/validators.py
sensenova/version.py
sensenova/api_resources/__init__.py
sensenova/api_resources/character_chat_completion.py
sensenova/api_resources/chat_completion.py
sensenova/api_resources/chat_conversations.py
sensenova/api_resources/completion.py
sensenova/api_resources/dataset.py
sensenova/api_resources/embedding.py
sensenova/api_resources/error_object.py
sensenova/api_resources/file.py
sensenova/api_resources/fine_tune.py
sensenova/api_resources/finetune_completion.py
sensenova/api_resources/knowledge_base.py
sensenova/api_resources/model.py
sensenova/api_resources/serving.py
sensenova/api_resources/abstract/__init__.py
sensenova/api_resources/abstract/api_resource.py
sensenova/api_resources/abstract/createable_api_resource.py
sensenova/api_resources/abstract/deletable_api_resource.py
sensenova/api_resources/abstract/downloadable_api_resource.py
sensenova/api_resources/abstract/engine_api_resource.py
sensenova/api_resources/abstract/file_api_resource.py
sensenova/api_resources/abstract/file_deletable_api_resource.py
sensenova/api_resources/abstract/fileable_api_resource.py
sensenova/api_resources/abstract/listable_api_resource.py
sensenova/api_resources/abstract/updateable_api_resource.py
sensenova/api_resources/abstract/uploadable_api_resource.py
sensenova/tests/__init__.py
sensenova/tests/test_character_chat_completion.py
sensenova/tests/test_chat_completion.py
sensenova/tests/test_chat_conversations.py
sensenova/tests/test_completion.py
sensenova/tests/test_datasets.py
sensenova/tests/test_embedding.py
sensenova/tests/test_file.py
sensenova/tests/test_fine_tunes.py
sensenova/tests/test_finetune_completion.py
sensenova/tests/test_knowlege_bases.py
sensenova/tests/test_models.py
sensenova-1.0.6.dist-info/LICENSE
sensenova-1.0.6.dist-info/METADATA
sensenova-1.0.6.dist-info/WHEEL
sensenova-1.0.6.dist-info/entry_points.txt
sensenova-1.0.6.dist-info/top_level.txt
sensenova-1.0.6.dist-info/RECORD
