Metadata-Version: 2.1
Name: sensenova
Version: 1.0.6
Summary: Python client library for the Sensenova API
Author: Sensetime
Requires-Python: >=3.7.1
License-File: LICENSE
Requires-Dist: requests (>=2.20)
Requires-Dist: PyJWT (==2.6.0)
Requires-Dist: tqdm
Requires-Dist: aiohttp
Requires-Dist: typing-extensions ; python_version < "3.8"
